vicodepy/__init__.py
vicodepy/__main__.py
vicodepy/about.py
vicodepy/app.py
vicodepy/assets/handle.png
vicodepy/assets/minus1.png
vicodepy/assets/minus10.png
vicodepy/assets/minus5.png
vicodepy/assets/plus.png
vicodepy/assets/plus1.png
vicodepy/assets/plus10.png
vicodepy/assets/plus5.png
vicodepy/assets/style.qss
vicodepy/assets.py
vicodepy/coders.py
vicodepy/command.py
vicodepy/config/config.yml
vicodepy/config.py
vicodepy/constants.py
vicodepy/cursor.py
vicodepy/data.py
vicodepy/event.py
vicodepy/exceptions.py
vicodepy/files.py
vicodepy/format.py
vicodepy/images.py
vicodepy/mainwindow.py
vicodepy/menu.py
vicodepy/message.py
vicodepy/occurrence.py
vicodepy/textedit.py
vicodepy/timeline.py
vicodepy/timepane.py
vicodepy/timescale.py
vicodepy/utils.py
vicodepy/video.py
vicodepy-0.12.9.dist-info/entry_points.txt
vicodepy-0.12.9.dist-info/WHEEL
vicodepy-0.12.9.dist-info/METADATA
vicodepy-0.12.9.dist-info/licenses/LICENSE
vicodepy-0.12.9.dist-info/RECORD
