Metadata-Version: 2.1
Name: vicodepy
Version: 0.12.9
Summary: Video coder for psychological experiments
License: GPL-3.0-or-later
Author-email: Rafael Laboissière <rafael.laboissiere@cnrs.fr>,Esteban Milleret <esteban.milleret@etu.univ-grenoble-alpes.fr>
Requires-Python: >=3.8
Requires-Dist: PySide6==6.6.2
Requires-Dist: appdirs>=1.4.4
Requires-Dist: colour>=0.1.5
Requires-Dist: docopt>=0.6.2
Requires-Dist: numpy==1.26.3
Requires-Dist: pandas>=2.2.2
Requires-Dist: pyyaml>=6.0.1
